{
    "total": [
        {
            "id": "100090431332852",
            "count": 0
        },
        {
            "id": "100039443777832",
            "count": 0
        },
        {
            "id": "100044760132536",
            "count": 0
        },
        {
            "id": "100070687844896",
            "count": 0
        },
        {
            "id": "100038180040008",
            "count": 0
        },
        {
            "id": "100037218437125",
            "count": 15
        },
        {
            "id": "100088202301568",
            "count": 0
        },
        {
            "id": "100026527530219",
            "count": 0
        },
        {
            "id": "100077241716000",
            "count": 0
        },
        {
            "id": "100068184010676",
            "count": 0
        },
        {
            "id": "100081153613119",
            "count": 0
        },
        {
            "id": "100090837656599",
            "count": 0
        },
        {
            "id": "100049088355393",
            "count": 0
        },
        {
            "id": "100083967391593",
            "count": 0
        },
        {
            "id": "100057351438022",
            "count": 0
        },
        {
            "id": "100016502560758",
            "count": 0
        },
        {
            "id": "100066268796140",
            "count": 0
        },
        {
            "id": "100094118895297",
            "count": 0
        },
        {
            "id": "100068790468214",
            "count": 0
        }
    ],
    "week": [
        {
            "id": "100090431332852",
            "count": 0
        },
        {
            "id": "100039443777832",
            "count": 0
        },
        {
            "id": "100044760132536",
            "count": 0
        },
        {
            "id": "100070687844896",
            "count": 0
        },
        {
            "id": "100038180040008",
            "count": 0
        },
        {
            "id": "100037218437125",
            "count": 15
        },
        {
            "id": "100088202301568",
            "count": 0
        },
        {
            "id": "100026527530219",
            "count": 0
        },
        {
            "id": "100077241716000",
            "count": 0
        },
        {
            "id": "100068184010676",
            "count": 0
        },
        {
            "id": "100081153613119",
            "count": 0
        },
        {
            "id": "100090837656599",
            "count": 0
        },
        {
            "id": "100049088355393",
            "count": 0
        },
        {
            "id": "100083967391593",
            "count": 0
        },
        {
            "id": "100057351438022",
            "count": 0
        },
        {
            "id": "100016502560758",
            "count": 0
        },
        {
            "id": "100066268796140",
            "count": 0
        },
        {
            "id": "100094118895297",
            "count": 0
        },
        {
            "id": "100068790468214",
            "count": 0
        }
    ],
    "day": [
        {
            "id": "100090431332852",
            "count": 0
        },
        {
            "id": "100039443777832",
            "count": 0
        },
        {
            "id": "100044760132536",
            "count": 0
        },
        {
            "id": "100070687844896",
            "count": 0
        },
        {
            "id": "100038180040008",
            "count": 0
        },
        {
            "id": "100037218437125",
            "count": 15
        },
        {
            "id": "100088202301568",
            "count": 0
        },
        {
            "id": "100026527530219",
            "count": 0
        },
        {
            "id": "100077241716000",
            "count": 0
        },
        {
            "id": "100068184010676",
            "count": 0
        },
        {
            "id": "100081153613119",
            "count": 0
        },
        {
            "id": "100090837656599",
            "count": 0
        },
        {
            "id": "100049088355393",
            "count": 0
        },
        {
            "id": "100083967391593",
            "count": 0
        },
        {
            "id": "100057351438022",
            "count": 0
        },
        {
            "id": "100016502560758",
            "count": 0
        },
        {
            "id": "100066268796140",
            "count": 0
        },
        {
            "id": "100094118895297",
            "count": 0
        },
        {
            "id": "100068790468214",
            "count": 0
        }
    ],
    "time": 1,
    "last": {
        "time": 1,
        "day": [
            {
                "id": "100090431332852",
                "count": 0
            },
            {
                "id": "100039443777832",
                "count": 0
            },
            {
                "id": "100044760132536",
                "count": 0
            },
            {
                "id": "100070687844896",
                "count": 0
            },
            {
                "id": "100038180040008",
                "count": 0
            },
            {
                "id": "100037218437125",
                "count": 0
            },
            {
                "id": "100088202301568",
                "count": 0
            },
            {
                "id": "100026527530219",
                "count": 0
            },
            {
                "id": "100077241716000",
                "count": 0
            },
            {
                "id": "100068184010676",
                "count": 0
            },
            {
                "id": "100081153613119",
                "count": 0
            },
            {
                "id": "100090837656599",
                "count": 0
            },
            {
                "id": "100049088355393",
                "count": 0
            },
            {
                "id": "100083967391593",
                "count": 0
            },
            {
                "id": "100057351438022",
                "count": 0
            },
            {
                "id": "100016502560758",
                "count": 0
            },
            {
                "id": "100066268796140",
                "count": 0
            },
            {
                "id": "100094118895297",
                "count": 0
            },
            {
                "id": "100022341782828",
                "count": 0
            },
            {
                "id": "100068790468214",
                "count": 0
            }
        ],
        "week": [
            {
                "id": "100090431332852",
                "count": 0
            },
            {
                "id": "100039443777832",
                "count": 0
            },
            {
                "id": "100044760132536",
                "count": 0
            },
            {
                "id": "100070687844896",
                "count": 0
            },
            {
                "id": "100038180040008",
                "count": 0
            },
            {
                "id": "100037218437125",
                "count": 0
            },
            {
                "id": "100088202301568",
                "count": 0
            },
            {
                "id": "100026527530219",
                "count": 0
            },
            {
                "id": "100077241716000",
                "count": 0
            },
            {
                "id": "100068184010676",
                "count": 0
            },
            {
                "id": "100081153613119",
                "count": 0
            },
            {
                "id": "100090837656599",
                "count": 0
            },
            {
                "id": "100049088355393",
                "count": 0
            },
            {
                "id": "100083967391593",
                "count": 0
            },
            {
                "id": "100057351438022",
                "count": 0
            },
            {
                "id": "100016502560758",
                "count": 0
            },
            {
                "id": "100066268796140",
                "count": 0
            },
            {
                "id": "100094118895297",
                "count": 0
            },
            {
                "id": "100022341782828",
                "count": 0
            },
            {
                "id": "100068790468214",
                "count": 0
            }
        ]
    }
}